onesource/__init__.py
onesource/main.py
onesource_cli-1.3.1.dist-info/METADATA
onesource_cli-1.3.1.dist-info/WHEEL
onesource_cli-1.3.1.dist-info/entry_points.txt
onesource_cli-1.3.1.dist-info/top_level.txt
onesource_cli-1.3.1.dist-info/RECORD
