Metadata-Version: 2.4
Name: onesource-cli
Version: 1.3.1
Summary: A vibe coding tool to aggregate project code for LLMs.
Home-page: https://github.com/TW-RF54732/OneSource
Author: lolLeo
Author-email: leo173842558@gmail.com
Classifier: Programming Language :: Python :: 3
Classifier: License :: OSI Approved :: MIT License
Classifier: Operating System :: OS Independent
Requires-Python: >=3.8
Requires-Dist: pathspec
Requires-Dist: pyperclip
Requires-Dist: tiktoken
Dynamic: author
Dynamic: author-email
Dynamic: classifier
Dynamic: description
Dynamic: description-content-type
Dynamic: home-page
Dynamic: requires-dist
Dynamic: requires-python
Dynamic: summary
